hbcal/__init__.py
hbcal/abbrev_set.py
hbcal/configuration_utilities.py
hbcal/main.py
hbcal/my_collections.py
hbcal/ordinal.py
hbcal/version.py
hbcal/hebrew_calendar/__init__.py
hbcal/hebrew_calendar/abs_time.py
hbcal/hebrew_calendar/abstract_attribute.py
hbcal/hebrew_calendar/civil_year.py
hbcal/hebrew_calendar/daf_yomi.py
hbcal/hebrew_calendar/date.py
hbcal/hebrew_calendar/format_percent_string.py
hbcal/hebrew_calendar/gematria.py
hbcal/hebrew_calendar/hebrew_letters.py
hbcal/hebrew_calendar/hebrew_year.py
hbcal/hebrew_calendar/weekday.py
hbcal/templates/help
hbcal-0.11.0.dist-info/LICENSE
hbcal-0.11.0.dist-info/METADATA
hbcal-0.11.0.dist-info/WHEEL
hbcal-0.11.0.dist-info/entry_points.txt
hbcal-0.11.0.dist-info/top_level.txt
hbcal-0.11.0.dist-info/RECORD
