Metadata-Version: 2.1
Name: hbcal
Version: 0.11.0
Summary: Hebrew Calendar Date Converter
Home-page: https://github.com/markastern/hbcal
Author: Mark Stern
Author-email: markalexstern@gmail.com
License: UNKNOWN
Platform: UNKNOWN
Requires-Python: >=2.7, !=3.0.*, !=3.1.*, !=3.2.*
Requires-Dist: future
Requires-Dist: python-bidi
Requires-Dist: functools32 ; python_version < "3.0"
Requires-Dist: enum34 ; python_version < "3.4"
Requires-Dist: cached-property ; python_version < "3.8"
